splitfasta/__init__.py
splitfasta/__main__.py
split_fasta-1.0.0.dist-info/LICENSE
split_fasta-1.0.0.dist-info/METADATA
split_fasta-1.0.0.dist-info/WHEEL
split_fasta-1.0.0.dist-info/entry_points.txt
split_fasta-1.0.0.dist-info/top_level.txt
split_fasta-1.0.0.dist-info/RECORD
