Metadata-Version: 2.1
Name: split-fasta
Version: 1.0.0
Summary: A Command Line tool for splitting Fasta file with multiple sequences into individual Fasta files.
Home-page: https://github.com/uditvashisht/split-fasta
Author: Udit Vashisht
Author-email: admin@saralgyaan.com
License: MIT
Platform: UNKNOWN
Classifier: License :: OSI Approved :: MIT License
Classifier: Programming Language :: Python :: 3.6
Classifier: Programming Language :: Python :: 3.7
Classifier: Programming Language :: Python :: 3.8
